benches/actor_mesh_benchmark.py
benches/startup.py
monarch/__init__.py
monarch/_rust_bindings.cpython-310-x86_64-linux-gnu.so
monarch/_testing.py
monarch/actor_mesh.py
monarch/bootstrap_main.py
monarch/cached_remote_function.py
monarch/fetch.py
monarch/gradient_generator.py
monarch/memory.py
monarch/mesh_controller.py
monarch/notebook.py
monarch/opaque_module.py
monarch/opaque_object.py
monarch/proc_mesh.py
monarch/profiler.py
monarch/python_local_mesh.py
monarch/random.py
monarch/remote_class.py
monarch/rust_backend_mesh.py
monarch/safe_torch.py
monarch/tensorboard.py
monarch/test_rust_bindings_import.py
monarch/world_mesh.py
monarch/_rust_bindings/__init__.pyi
monarch/_rust_bindings/old.pyi
monarch/_rust_bindings/rdma.pyi
monarch/_rust_bindings/controller/bootstrap.pyi
monarch/_rust_bindings/monarch_extension/__init__.pyi
monarch/_rust_bindings/monarch_extension/blocking.pyi
monarch/_rust_bindings/monarch_extension/client.pyi
monarch/_rust_bindings/monarch_extension/code_sync.pyi
monarch/_rust_bindings/monarch_extension/controller.pyi
monarch/_rust_bindings/monarch_extension/debugger.pyi
monarch/_rust_bindings/monarch_extension/logging.pyi
monarch/_rust_bindings/monarch_extension/mesh_controller.pyi
monarch/_rust_bindings/monarch_extension/panic.pyi
monarch/_rust_bindings/monarch_extension/simulation_tools.pyi
monarch/_rust_bindings/monarch_extension/tensor_worker.pyi
monarch/_rust_bindings/monarch_extension/trace.pyi
monarch/_rust_bindings/monarch_hyperactor/actor.pyi
monarch/_rust_bindings/monarch_hyperactor/actor_mesh.pyi
monarch/_rust_bindings/monarch_hyperactor/alloc.pyi
monarch/_rust_bindings/monarch_hyperactor/bootstrap.pyi
monarch/_rust_bindings/monarch_hyperactor/buffers.pyi
monarch/_rust_bindings/monarch_hyperactor/channel.pyi
monarch/_rust_bindings/monarch_hyperactor/config.pyi
monarch/_rust_bindings/monarch_hyperactor/context.pyi
monarch/_rust_bindings/monarch_hyperactor/mailbox.pyi
monarch/_rust_bindings/monarch_hyperactor/proc.pyi
torchmonarch_nightly-2026.1.9.dist-info/licenses/LICENSE
torchmonarch_nightly-2026.1.9.dist-info/METADATA
torchmonarch_nightly-2026.1.9.dist-info/WHEEL
torchmonarch_nightly-2026.1.9.dist-info/entry_points.txt
torchmonarch_nightly-2026.1.9.dist-info/top_level.txt
torchmonarch_nightly-2026.1.9.dist-info/RECORD
