Metadata-Version: 2.4
Name: torchmonarch-nightly
Version: 2026.1.9
Summary: Monarch: Single controller library
Author-email: Meta <oncall+monarch@xmail.facebook.com>
License: BSD-3-Clause
Requires-Python: >=3.10
License-File: LICENSE
Requires-Dist: pyzmq
Requires-Dist: requests
Requires-Dist: numpy
Requires-Dist: pyre-extensions
Requires-Dist: typing-extensions>=4.12
Requires-Dist: cloudpickle
Requires-Dist: torchx-nightly
Requires-Dist: lark
Requires-Dist: tabulate
Requires-Dist: opentelemetry-api
Requires-Dist: clusterscope
Requires-Dist: torch
Provides-Extra: examples
Requires-Dist: bs4; extra == "examples"
Requires-Dist: ipython; extra == "examples"
Requires-Dist: psutil; extra == "examples"
Provides-Extra: test
Requires-Dist: pytest; extra == "test"
Requires-Dist: pytest-timeout; extra == "test"
Requires-Dist: pytest-asyncio; extra == "test"
Requires-Dist: pytest-xdist; extra == "test"
Requires-Dist: pyright; extra == "test"
Provides-Extra: kubernetes
Requires-Dist: kubernetes; extra == "kubernetes"
Dynamic: license-file
